<produk>
    <item>
        <nama>Tempe Oishi</nama>
        <ukuran>150 Gram</ukuran>
        <gambar>img/product-150.png</gambar>
        <link>https://s.shopee.co.id/3qAkneCiBm</link>
    </item>
    <item>
        <nama>Tempe Oishi</nama>
        <ukuran>250 Gram</ukuran>
        <gambar>img/product-250.png</gambar>
        <link>https://shopee.co.id/Oishi-Tempe-Higienis-250gr-i.763649325.28786776869</link>
    </item>
    <item>
        <nama>Tempe Oishi</nama>
        <ukuran>450 Gram</ukuran>
        <gambar>img/product-450.png</gambar>
        <link>https://s.shopee.co.id/AKOEXXfHNI</link>
    </item>
</produk>
